{"_type":"export","__export_format":4,"__export_date":"2020-07-27T18:56:56.242Z","__export_source":"insomnia.desktop.app:v2020.2.2","resources":[{"_id":"req_14689b26d03345d98e4e1ae956ed4088","authentication":{},"body":{},"created":1593979369652,"description":"","headers":[],"isPrivate":false,"metaSortKey":-1593979369652,"method":"GET","modified":1595866397867,"name":"api/ - Read-all","parameters":[],"parentId":"wrk_6d96af9790a6461ab999998019fffa0b","settingDisableRenderRequestBody":false,"settingEncodeUrl":true,"settingFollowRedirects":"global","settingRebuildPath":true,"settingSendCookies":true,"settingStoreCookies":true,"url":"{{ SERVER_URL  }}{{ PORT  }}{{ API  }}","_type":"request"},{"_id":"wrk_6d96af9790a6461ab999998019fffa0b","created":1593957109266,"description":"","modified":1593957109266,"name":"DoIt","parentId":null,"scope":null,"_type":"workspace"},{"_id":"req_97ef5ef16c6a44648a297b813f02c244","authentication":{},"body":{"mimeType":"application/json","text":"{\n\t\"description\": \"asdfasdf\",\n\t\"done\": false\n}"},"created":1595866582046,"description":"","headers":[{"id":"pair_1122abf3ac7744cfbb2eb3fb79e7ef7b","name":"Content-Type","value":"application/json"}],"isPrivate":false,"metaSortKey":-1593979369602,"method":"POST","modified":1595866731758,"name":"api/ - Insert-one","parameters":[],"parentId":"wrk_6d96af9790a6461ab999998019fffa0b","settingDisableRenderRequestBody":false,"settingEncodeUrl":true,"settingFollowRedirects":"global","settingRebuildPath":true,"settingSendCookies":true,"settingStoreCookies":true,"url":"{{ SERVER_URL  }}{{ PORT  }}{{ API  }}","_type":"request"},{"_id":"req_10301d2d7d084e8fb29b89fceb96f38f","authentication":{},"body":{"mimeType":"application/json","text":"{\n\t\"description\": \"asdfasdf\",\n\t\"done\": false\n}"},"created":1595866719841,"description":"","headers":[{"id":"pair_1122abf3ac7744cfbb2eb3fb79e7ef7b","name":"Content-Type","value":"application/json"}],"isPrivate":false,"metaSortKey":-1593979369552,"method":"PUT","modified":1595866756825,"name":"api/ - Update-one","parameters":[],"parentId":"wrk_6d96af9790a6461ab999998019fffa0b","settingDisableRenderRequestBody":false,"settingEncodeUrl":true,"settingFollowRedirects":"global","settingRebuildPath":true,"settingSendCookies":true,"settingStoreCookies":true,"url":"{{ SERVER_URL  }}{{ PORT  }}{{ API  }}/2","_type":"request"},{"_id":"req_cb648fc3b4a144beab459e5f8b3a175b","authentication":{},"body":{"mimeType":"application/json","text":"{\n\t\"description\": \"asdfasdf\",\n\t\"done\": false\n}"},"created":1595867241317,"description":"","headers":[{"id":"pair_1122abf3ac7744cfbb2eb3fb79e7ef7b","name":"Content-Type","value":"application/json"}],"isPrivate":false,"metaSortKey":-1593979369502,"method":"DELETE","modified":1595867258648,"name":"api/ - Delete-one","parameters":[],"parentId":"wrk_6d96af9790a6461ab999998019fffa0b","settingDisableRenderRequestBody":false,"settingEncodeUrl":true,"settingFollowRedirects":"global","settingRebuildPath":true,"settingSendCookies":true,"settingStoreCookies":true,"url":"{{ SERVER_URL  }}{{ PORT  }}{{ API  }}/1","_type":"request"},{"_id":"env_46af1303dd9ba638012ca66b393e0efe4c94f3bd","color":null,"created":1593957109366,"data":{"API":"/api","PORT":8080,"SERVER_URL":"http://0.0.0.0:"},"dataPropertyOrder":{"&":["SERVER_URL","PORT","API"]},"isPrivate":false,"metaSortKey":1593957109366,"modified":1595866338533,"name":"Base Environment","parentId":"wrk_6d96af9790a6461ab999998019fffa0b","_type":"environment"},{"_id":"jar_46af1303dd9ba638012ca66b393e0efe4c94f3bd","cookies":[],"created":1593957109379,"modified":1593957109379,"name":"Default Jar","parentId":"wrk_6d96af9790a6461ab999998019fffa0b","_type":"cookie_jar"},{"_id":"spc_73c33b906d2c4d08a802e30edf60dc46","contentType":"yaml","contents":"","created":1593957109278,"fileName":"DoIt","modified":1593957109278,"parentId":"wrk_6d96af9790a6461ab999998019fffa0b","_type":"api_spec"}]}